truestate/__init__.py
truestate/client.py
truestate/exceptions.py
truestate/artifacts/__init__.py
truestate/artifacts/classification.py
truestate/artifacts/manager.py
truestate/datasets/__init__.py
truestate/datasets/dataset.py
truestate/datasets/manager.py
truestate/datasets/types.py
truestate/inference/__init__.py
truestate/inference/embedding_search.py
truestate/inference/hierarchy_classification.py
truestate/inference/routing.py
truestate/inference/universal_classification.py
truestate/jobs/__init__.py
truestate/jobs/job.py
truestate/jobs/types.py
truestate/jobs/utils.py
truestate/jobs/data/__init__.py
truestate/jobs/data/transform.py
truestate/jobs/data/types.py
truestate/jobs/integrations/__init__.py
truestate/jobs/integrations/read.py
truestate/jobs/integrations/types.py
truestate/jobs/ml/__init__.py
truestate/jobs/ml/text/__init__.py
truestate/jobs/ml/text/category/__init__.py
truestate/jobs/ml/text/category/text_classifier.py
truestate/jobs/ml/text/category/types.py
truestate/jobs/ml/text/continuous/__init__.py
truestate/jobs/ml/text/continuous/text_preference_model.py
truestate/jobs/ml/text/embedding/__init__.py
truestate/jobs/ml/text/embedding/apply_embedding.py
truestate/jobs/ml/text/text/__init__.py
truestate/jobs/ml/text/text/apply_sequence_model.py
truestate/jobs/ml/text/text/supervised_finetuning.py
truestate/jobs/ml/text/universal_classification/__init__.py
truestate/jobs/ml/text/universal_classification/apply_hierarchy_classification.py
truestate/jobs/ml/text/universal_classification/apply_universal_classification.py
truestate/models/__init__.py
truestate/models/manager.py
truestate/models/model.py
truestate/models/types.py
truestate/secrets/__init__.py
truestate/secrets/manager.py
truestate/secrets/models.py
truestate/workflows/__init__.py
truestate/workflows/manager.py
truestate/workflows/models.py
truestate/workflows/workflow.py
truestate-0.7.8.dist-info/LICENSE
truestate-0.7.8.dist-info/METADATA
truestate-0.7.8.dist-info/WHEEL
truestate-0.7.8.dist-info/top_level.txt
truestate-0.7.8.dist-info/RECORD
